README.md
setup.py
greendeck_proxygrabber/__init__.py
greendeck_proxygrabber.egg-info/PKG-INFO
greendeck_proxygrabber.egg-info/SOURCES.txt
greendeck_proxygrabber.egg-info/dependency_links.txt
greendeck_proxygrabber.egg-info/not-zip-safe
greendeck_proxygrabber.egg-info/requires.txt
greendeck_proxygrabber.egg-info/top_level.txt
greendeck_proxygrabber/src/proxygrabber/__init__.py
greendeck_proxygrabber/src/proxygrabber/constant.py
greendeck_proxygrabber/src/proxygrabber/country_proxy_grabber.py
greendeck_proxygrabber/src/proxygrabber/proxychecker.py
greendeck_proxygrabber/src/proxygrabber/proxygrabber.py