Metadata-Version: 2.1
Name: greendeck-proxygrabber
Version: 0.3.5
Summary: Greendeck Proxy Grabber Package
Home-page: https://github.com/gagan1510/greendeck-proxygrabber
Author: gagan singh k
Author-email: gaganpreet.gs007@gmail.com
License: UNKNOWN
Platform: UNKNOWN
Classifier: Programming Language :: Python :: 3
Classifier: License :: OSI Approved :: MIT License
Classifier: Operating System :: OS Independent
